MANIFEST.in
README.rst
UNLICENSE
manage.py
setup.py
assets/guardian-sketch.png
django_sslify.egg-info/PKG-INFO
django_sslify.egg-info/SOURCES.txt
django_sslify.egg-info/dependency_links.txt
django_sslify.egg-info/not-zip-safe
django_sslify.egg-info/requires.txt
django_sslify.egg-info/top_level.txt
sslify/__init__.py
sslify/middleware.py
sslify/models.py
sslify/tests.py
sslify/views.py
test_project/__init__.py
test_project/settings.py
test_project/templates.py
test_project/urls.py
test_project/wsgi.py